derotation/__init__.py
derotation/derotate_batch.py
derotation/derotate_by_line.py
derotation/sample_data.py
derotation/analysis/bayesian_optimization.py
derotation/analysis/blob_detection.py
derotation/analysis/fit_ellipse.py
derotation/analysis/full_derotation_pipeline.py
derotation/analysis/incremental_derotation_pipeline.py
derotation/analysis/mean_images.py
derotation/analysis/metrics.py
derotation/config/config_template.yml
derotation/config/load_config.py
derotation/load_data/custom_data_loaders.py
derotation/plotting_hooks/for_derotation.py
derotation/simulate/line_scanning_microscope.py
derotation/simulate/synthetic_data.py
derotation-0.1.5.dist-info/licenses/LICENSE
derotation-0.1.5.dist-info/METADATA
derotation-0.1.5.dist-info/WHEEL
derotation-0.1.5.dist-info/top_level.txt
derotation-0.1.5.dist-info/RECORD
