Metadata-Version: 2.4
Name: derotation
Version: 0.1.5
Summary: Derotate multiphoton calcium imaging movies
Author-email: Laura Porta <l.porta@ucl.ac.uk>
License: BSD-3-Clause
Project-URL: Homepage, https://github.com/neuroinformatics-unit/derotation
Project-URL: Bug Tracker, https://github.com/neuroinformatics-unit/derotation/issues
Project-URL: Documentation, https://neuroinformatics-unit.github.io/derotation
Project-URL: Source Code, https://github.com/neuroinformatics-unit/derotation
Project-URL: User Support, https://github.com/neuroinformatics-unit/derotation/issues
Classifier: Development Status :: 2 - Pre-Alpha
Classifier: Programming Language :: Python
Classifier: Programming Language :: Python :: 3
Classifier: Programming Language :: Python :: 3.10
Classifier: Programming Language :: Python :: 3.11
Classifier: Programming Language :: Python :: 3.12
Classifier: Operating System :: OS Independent
Classifier: License :: OSI Approved :: BSD License
Requires-Python: >=3.10.0
License-File: LICENSE
Requires-Dist: numpy
Requires-Dist: tifffile
Requires-Dist: matplotlib
Requires-Dist: scipy
Requires-Dist: PyYAML
Requires-Dist: fancylog
Requires-Dist: matplotlib
Requires-Dist: pandas
Requires-Dist: tqdm
Requires-Dist: scikit-learn
Requires-Dist: scikit-image
Requires-Dist: bayesian-optimization
Requires-Dist: pooch
Provides-Extra: dev
Requires-Dist: pytest; extra == "dev"
Requires-Dist: pytest-cov; extra == "dev"
Requires-Dist: coverage; extra == "dev"
Requires-Dist: tox; extra == "dev"
Requires-Dist: black; extra == "dev"
Requires-Dist: mypy; extra == "dev"
Requires-Dist: pre-commit; extra == "dev"
Requires-Dist: ruff; extra == "dev"
Requires-Dist: setuptools_scm; extra == "dev"
Dynamic: license-file
